<?xml version="1.0" encoding="UTF-8"?>
<beans xmlns="http://www.springframework.org/schema/beans"
       xmlns:xsi="http://www.w3.org/2001/XMLSchema-instance"
       xmlns:batch="http://www.springframework.org/schema/batch"
       xmlns:context="http://www.springframework.org/schema/context"
       xmlns:bean="http://www.springframework.org/schema/beans" xmlns:util="http://www.springframework.org/schema/util"
       xsi:schemaLocation="http://www.springframework.org/schema/beans
                           http://www.springframework.org/schema/beans/spring-beans.xsd
		                   http://www.springframework.org/schema/batch
                           http://www.springframework.org/schema/batch/spring-batch.xsd
		                   http://www.springframework.org/schema/context
                           http://www.springframework.org/schema/context/spring-context.xsd
                           http://www.springframework.org/schema/util
                           http://www.springframework.org/schema/util/spring-util-3.1.xsd">

    <description>
        This job generate the XML for a ExpressionAtlas to be submitted to OmicsDI system.
    </description>

    <import resource="../context/common-context.xml"/>
    <import resource="../context/db-job-repository.xml"/>
    <import resource="../context/mongo-db-context.xml" />



    <batch:job id="ddiImportJob" xmlns="http://www.springframework.org/schema/batch">

        <batch:step id="generateBaselineXML" parent="parentStep" next="generateRelativeXML">
            <batch:tasklet>
                <bean:bean id="generateBaselineXMLStep" scope="step" class="uk.ac.ebi.ddi.pipeline.indexer.tasklet.generation.GenerateEBeyeExpressionAtlasXML">
                    <bean:property name="experimentFileName" value="${ddi.common.expressionatlas.baseline.experiment.file}"/>
                    <bean:property name="geneFileName" value="${ddi.common.expressionatlas.baseline.gene.file}"/>
                    <bean:property name="outputFile"  value="${ddi.common.original.directory}${ddi.common.expressionatlas.database.index}/${ddi.common.expressionatlas.baseline.original.file}" />
                </bean:bean>
            </batch:tasklet>
        </batch:step>

        <batch:step id="generateRelativeXML" parent="parentStep" next="validateXMLStep">
            <batch:tasklet>
                <bean:bean id="generateRelativeXMLStep" scope="step" class="uk.ac.ebi.ddi.pipeline.indexer.tasklet.generation.GenerateEBeyeExpressionAtlasXML">
                    <bean:property name="experimentFileName" value="${ddi.common.expressionatlas.relative.experiment.file}"/>
                    <bean:property name="geneFileName" value="${ddi.common.expressionatlas.relative.gene.file}"/>
                    <bean:property name="outputFile"  value="${ddi.common.original.directory}${ddi.common.expressionatlas.database.index}/${ddi.common.expressionatlas.relative.original.file}" />
                </bean:bean>
            </batch:tasklet>
        </batch:step>

        <batch:step id="validateXMLStep" parent="parentStep" next="splitterStep">
            <batch:tasklet>
                <bean:bean id="validateEbEXmlTasklet" scope="step" class="uk.ac.ebi.ddi.pipeline.indexer.tasklet.validation.ValidationOriginalDataTasklet">
                    <bean:property name="directory" value="${ddi.common.original.directory}${ddi.common.expressionatlas.database.index}"/>
                    <bean:property name="reportName" value="${ddi.common.original.report.name}"/>
                </bean:bean>
            </batch:tasklet>
        </batch:step>

        <batch:step id="splitterStep" parent="parentStep" next="importDataStep">
            <batch:tasklet>
                <bean:bean id="splitterTasklet" scope="step" class="uk.ac.ebi.ddi.pipeline.indexer.tasklet.io.SplitterFromSource">
                    <bean:property name="inputDirectory"  value="file:${ddi.common.original.directory}${ddi.common.expressionatlas.database.index}"/>
                    <bean:property name="outputDirectory" value="file:${ddi.common.data.directory}${ddi.common.expressionatlas.database.index}"/>
                    <bean:property name="originalPrefix"  value="${ddi.common.original.expressionatlas.prefix}" />
                    <bean:property name="numberEntries"   value="${ddi.common.multiple.file.number.entries}"/>
                    <bean:property name="filePrefix"      value="${ddi.common.expressionatlas.prefix}" />
                </bean:bean>
            </batch:tasklet>
        </batch:step>

        <batch:step id="importDataStep" parent="parentStep" next="annotationFiles">
            <batch:tasklet>
                <bean:bean id="annotationTasklet" scope="step" class="uk.ac.ebi.ddi.pipeline.indexer.tasklet.database.DatasetImportTasklet">
                    <bean:property name="inputDirectory" value="file:${ddi.common.data.directory}${ddi.common.expressionatlas.database.index}"/>
                    <bean:property name="datasetAnnotationService" ref="datasetAnnotationService" />
                    <bean:property name="databaseAnnotationService" ref="databaseAnnotationService" />
                    <bean:property name="databaseName" value="${ddi.common.expressionatlas.database.name}" />
                </bean:bean>
            </batch:tasklet>
        </batch:step>

        <batch:step id="annotationFiles" parent="parentStep" next="datasetFileRetrieve">
            <batch:tasklet>
                <bean:bean id="annotationArrayExpressTasklet" scope="step" class="uk.ac.ebi.ddi.pipeline.indexer.tasklet.annotation.ExpressionAtlasAnnotationTasklet">
                    <bean:property name="databaseName" value="${ddi.common.expressionatlas.database.name}"/>
                    <bean:property name="originalDatabase" value="${ddi.common.arrayexpress.database.name}" />
                    <bean:property name="datasetAnnotationService" ref="datasetAnnotationService" />
                </bean:bean>
            </batch:tasklet>
        </batch:step>

<!--        <batch:step id="annotationFiles" parent="parentStep">
            <batch:tasklet>
                <bean:bean id="annotationArrayExpressTasklet" scope="step" class="uk.ac.ebi.ddi.pipeline.indexer.tasklet.annotation.ExpressionAtlasAnnotationTasklet">
                    <bean:property name="databaseName" value="${ddi.common.expressionatlas.database.name}"/>
                    <bean:property name="originalDatabase" value="${ddi.common.arrayexpress.database.name}" />
                    <bean:property name="datasetAnnotationService" ref="datasetAnnotationService" />
                </bean:bean>
            </batch:tasklet>
        </batch:step>-->

        <batch:step id="datasetFileRetrieve" parent="parentStep" next="cleanStep">
            <batch:tasklet>
                <bean:bean id="retrieveFileUrlStep" scope="step" class="uk.ac.ebi.ddi.pipeline.indexer.tasklet.dataset.DatasetFileUrlRetrieveTasklet">
                    <bean:property name="datasetService" ref="datasetService" />
                    <bean:property name="databaseDetailService" ref="databaseDetailService" />
                    <bean:property name="overwrite" value="false" />
                    <bean:property name="databaseName" value="${ddi.common.expressionatlas.database.name}"/>
                </bean:bean>
            </batch:tasklet>
        </batch:step>

        <batch:step id="cleanStep" next="moveToProductionStep" parent="parentStep">
            <batch:tasklet>
                <bean:bean id="cleanTasklet" scope="step" class="uk.ac.ebi.ddi.pipeline.indexer.tasklet.io.CleanDirectoryTasklet">
                    <bean:property name="inputDirectory" value="file:${ddi.common.prod.directory}${ddi.common.expressionatlas.database.index}" />
                </bean:bean>
            </batch:tasklet>
        </batch:step>

        <batch:step id="moveToProductionStep" parent="parentStep">
            <batch:tasklet>
                <bean:bean id="generateFromSourceTasklet" scope="step" class="uk.ac.ebi.ddi.pipeline.indexer.tasklet.database.DatasetExportTasklet">
                    <bean:property name="databaseName" value="${ddi.common.expressionatlas.database.name}" />
                    <bean:property name="outputDirectory" value="file:${ddi.common.prod.directory}${ddi.common.expressionatlas.database.index}"/>
                    <bean:property name="filePrefix"      value="${ddi.common.expressionatlas.prefix}" />
                    <bean:property name="numberEntries"   value="${ddi.common.multiple.file.number.entries}" />
                    <bean:property name="databaseService" ref="databaseAnnotationService" />
                    <bean:property name="datasetAnnotationService"  ref="datasetAnnotationService" />
                </bean:bean>
            </batch:tasklet>
        </batch:step>

        <batch:listeners>
            <batch:listener ref="jobListener"/>
        </batch:listeners>
    </batch:job>

    <batch:job id="similarityJob">
        <batch:step id="importTerms" parent="parentStep" next="similarityStep">
            <batch:tasklet>
                <bean:bean id="importTermsTasklet" scope="step" class="uk.ac.ebi.ddi.pipeline.indexer.tasklet.similarity.UpdateTermsTasklet">
                    <bean:property name="databaseName" value="${ddi.common.expressionatlas.database.name}" />
                    <bean:property name="datasetAnnotationService" ref="datasetAnnotationService" />
                    <bean:property name="dataType" >
                        <util:constant static-field="uk.ac.ebi.ddi.annotation.utils.DataType.TRANSCRIPTOMIC_DATA"/>
                    </bean:property>
                    <bean:property name="ddiExpDataImportService" ref="ddiExpDataImportService" />
                </bean:bean>
            </batch:tasklet>
        </batch:step>

        <batch:step id="similarityStep" parent="parentStep">
            <batch:tasklet>
                <bean:bean id="similarityScoreTasklet" scope="step" class="uk.ac.ebi.ddi.pipeline.indexer.tasklet.similarity.SimilaryScoreTasklet">
                    <bean:property name="typeOfData" ref="dataTypesTrancriptomics" />
                    <bean:property name="mongoTemplate" ref="mongoTemplate" />
                    <bean:property name="termInDBService" ref="termInDBService"/>
                    <bean:property name="ddiExpDataImportService" ref="ddiExpDataImportService"/>
                    <bean:property name="ddiExpDataProcessService" ref="ddiExpDataProcessService"/>
                    <bean:property name="expOutputDatasetService" ref="expOutputDatasetService" />
                </bean:bean>
            </batch:tasklet>
        </batch:step>
    </batch:job>

    <batch:job id="ddiEnrichmentJob" xmlns="http://www.springframework.org/schema/batch">
        <batch:step id="enrichmentStep" parent="parentStep">
            <batch:tasklet>
                <bean:bean id="enrichmentTask" scope="step" class="uk.ac.ebi.ddi.pipeline.indexer.tasklet.enrichment.EnrichmentXMLTasklet">
                    <bean:property name="databaseName" value="${ddi.common.expressionatlas.database.name}" />
                    <bean:property name="annotationService" ref="annotationService"/>
                    <bean:property name="datasetAnnotationService" ref="datasetAnnotationService" />
                    <bean:property name="databaseAnnotationService" ref="databaseAnnotationService" />
                </bean:bean>
            </batch:tasklet>
        </batch:step>
    </batch:job>

    <batch:job id="generatetionJob" xmlns="http://www.springframework.org/schema/batch">

        <batch:step id="cleanStepJob" next="moveToProductionStepJob" parent="parentStep">
            <batch:tasklet>
                <bean:bean id="cleanJobTasklet" scope="step" class="uk.ac.ebi.ddi.pipeline.indexer.tasklet.io.CleanDirectoryTasklet">
                    <bean:property name="inputDirectory" value="file:${ddi.common.prod.directory}${ddi.common.expressionatlas.database.index}" />
                </bean:bean>
            </batch:tasklet>
        </batch:step>

        <batch:step id="moveToProductionStepJob" parent="parentStep">
            <batch:tasklet>
                <bean:bean id="generateFromSourceJobTasklet" scope="step" class="uk.ac.ebi.ddi.pipeline.indexer.tasklet.database.DatasetExportTasklet">
                    <bean:property name="databaseName" value="${ddi.common.expressionatlas.database.name}" />
                    <bean:property name="outputDirectory" value="file:${ddi.common.prod.directory}${ddi.common.expressionatlas.database.index}"/>
                    <bean:property name="filePrefix"      value="${ddi.common.expressionatlas.prefix}" />
                    <bean:property name="numberEntries"   value="${ddi.common.multiple.file.number.entries}" />
                    <bean:property name="databaseService" ref="databaseAnnotationService" />
                    <bean:property name="datasetAnnotationService"  ref="datasetAnnotationService" />
                </bean:bean>
            </batch:tasklet>
        </batch:step>
    </batch:job>

    <batch:step id="parentStep" abstract="true">
        <batch:listeners>
            <batch:listener ref="executionContextPromotionListener"/>
            <batch:listener ref="throwablePromotionListener"/>
        </batch:listeners>
    </batch:step>

    <bean id="dataTypesTrancriptomics" class="java.util.ArrayList">
        <constructor-arg>
            <list>
                <util:constant static-field="uk.ac.ebi.ddi.annotation.utils.DataType.TRANSCRIPTOMIC_DATA"/>
            </list>
        </constructor-arg>
    </bean>

    <!--listener for promoting properties in step execution context to job execution context-->
    <bean:bean id="executionContextPromotionListener" class="org.springframework.batch.core.listener.ExecutionContextPromotionListener">
        <bean:property name="keys">
            <bean:array>
                <bean:value>public.path.fragment</bean:value>
                <!-- added by getAndStoreOrigPublicationDateTaskletStep; used by genPublicSearchParamsStep -->
            </bean:array>
        </bean:property>
        <bean:property name="strict" value="false"/>
    </bean:bean>

    <!--load property files-->
    <context:property-placeholder location="classpath:prop/common.properties" ignore-unresolvable="true" order="1"/>

</beans>
